[
  {
    "_id": "7rcedckjb",
    "userId": "lqeuodaip",
    "productId": "he3rwv6qu",
    "rating": 5,
    "comment": "This Aditi Choker is breathtakingly gorgeous! The 22k gold glows warmly and the craftsmanship details are top notch. Worth every single rupee!",
    "createdAt": "2026-05-26T06:48:29.867Z"
  },
  {
    "_id": "o5pqak790",
    "userId": "lqeuodaip",
    "productId": "iiu6iaq57",
    "rating": 4,
    "comment": "A beautiful solitaire diamond. Clean cut, high clarity. The packaging from Shrii Navrang Jewellers felt so premium.",
    "createdAt": "2026-05-26T06:48:29.880Z"
  }
]